<?xml version="1.0" encoding="UTF-8"?>
<executable>
  <category>Examples</category>
  <title>antsRegistrationCLI</title>
  <description><![CDATA[This is a CLI module that can be bundled in an extension]]></description>
  <version>0.0.1</version>
  <documentation-url>http://www.example.com/Slicer/Modules/antsRegistrationCLI</documentation-url>
  <license>Slicer</license>
  <contributor>FirstName LastName (Institution), FirstName LastName (Institution)</contributor>
  <acknowledgements>This work was partially funded by NIH grant NXNNXXNNNNNN-NNXN</acknowledgements>
  
  <parameters>
    <label>Command</label>
    <description><![CDATA[ANTs Registration Command]]></description>
    <string>
      <name>antsCommand</name>
      <label>ANTs Registration Command</label>
      <channel>input</channel>
      <longflag>--antsCommand</longflag>
      <description><![CDATA[specify the antsRegistration command without the output argument]]></description>
    </string>
  </parameters>

  <parameters>
    <label>Output</label>
    <image>
      <name>outputVolume</name>
      <label>Output Volume</label>
      <channel>output</channel>
      <longflag>--outputVolume</longflag>
      <description><![CDATA[Output Volume.]]></description>
    </image>
    <transform fileExtensions="Composite.h5">
      <name>outputCompositeTransform</name>
      <label>Output Composite Transform</label>
      <channel>output</channel>
      <longflag>--outputCompositeTransform</longflag>
      <description><![CDATA[Output composite transform. If using composite transform don't specify a displacement field]]></description>
    </transform>
    <transform fileExtensions=".nii.gz">
      <name>outputDisplacementField</name>
      <label>Output Displacement Field</label>
      <channel>output</channel>
      <longflag>--outputDisplacementField</longflag>
      <description><![CDATA[Output displacement field. If using displacement field don't specify a composite transform]]></description>
    </transform>
  </parameters>

</executable>
